translators/__init__.py
translators/cli.py
translators/server.py
translators/server_async.py
translators-6.0.4.dist-info/licenses/LICENSE
translators-6.0.4.dist-info/METADATA
translators-6.0.4.dist-info/WHEEL
translators-6.0.4.dist-info/entry_points.txt
translators-6.0.4.dist-info/top_level.txt
translators-6.0.4.dist-info/RECORD
