Metadata-Version: 2.4
Name: translators
Version: 6.0.4
Summary: Translators is a library that aims to bring free, multiple, enjoyable translations to individuals and students in Python.
Home-page: https://github.com/uliontse/translators
Author: UlionTse
Author-email: uliontse@outlook.com
License: GPLv3
Project-URL: Source, https://github.com/UlionTse/translators
Project-URL: Changelog, https://github.com/UlionTse/translators/blob/master/change_log.md
Project-URL: Documentation, https://github.com/UlionTse/translators/blob/master/README.md
Keywords: translate,translate_text,translate_html,alibaba,apertium,argos,baidu,bing,caiyun,cloudTranslation,deepl,elia,google,hujiang,iciba,iflytek,iflyrec,itranslate,judic,languageWire,lara,lingvanex,mglip,mirai,modernMt,myMemory,niutrans,papago,qqFanyi,qqTranSmart,reverso,sogou,sysTran,tilde,translateCom,translateMe,utibet,volcEngine,xunjie,yandex,yeekit,youdao
Classifier: Development Status :: 5 - Production/Stable
Classifier: Environment :: Web Environment
Classifier: Intended Audience :: Developers
Classifier: License :: OSI Approved :: GNU General Public License v3 (GPLv3)
Classifier: Programming Language :: Python :: 3 :: Only
Classifier: Programming Language :: Python :: 3.8
Classifier: Programming Language :: Python :: 3.9
Classifier: Programming Language :: Python :: 3.10
Classifier: Programming Language :: Python :: 3.11
Classifier: Programming Language :: Python :: 3.12
Classifier: Programming Language :: Python :: 3.13
Requires-Python: >=3.8
License-File: LICENSE
Requires-Dist: httpx>=0.28.1
Requires-Dist: requests>=2.32.3
Requires-Dist: niquests>=3.14.0
Requires-Dist: exejs>=0.0.7
Requires-Dist: lxml>=5.4.0
Requires-Dist: tqdm>=4.67.1
Requires-Dist: pathos>=0.3.4
Requires-Dist: ai-cloudscraper>=3.7.6
Requires-Dist: cryptography>=42.0.4
Requires-Dist: brotlicffi>=1.2.0.0
Requires-Dist: brotli>=1.2.0
Provides-Extra: pypi
Requires-Dist: build>=1.4.0; extra == "pypi"
Requires-Dist: twine>=6.2.0; extra == "pypi"
Requires-Dist: setuptools>=75.3.0; extra == "pypi"
Dynamic: author
Dynamic: author-email
Dynamic: classifier
Dynamic: description
Dynamic: description-content-type
Dynamic: home-page
Dynamic: keywords
Dynamic: license
Dynamic: license-file
Dynamic: project-url
Dynamic: provides-extra
Dynamic: requires-dist
Dynamic: requires-python
Dynamic: summary
